minha_biblioteca/__init__.py
minha_biblioteca/exemplo.py
minha_biblioteca_nersant_basica_inicial-0.1.0.dist-info/METADATA
minha_biblioteca_nersant_basica_inicial-0.1.0.dist-info/WHEEL
minha_biblioteca_nersant_basica_inicial-0.1.0.dist-info/top_level.txt
minha_biblioteca_nersant_basica_inicial-0.1.0.dist-info/RECORD
