Metadata-Version: 2.4
Name: minha-biblioteca-nersant-basica-inicial
Version: 0.1.0
Summary: Uma biblioteca de exemplo criada no curso
Author-email: Marcelo Kamei <marcelokamei78@gmail.com>
License: MIT
Requires-Python: >=3.8
